dnadna/__init__.py
dnadna/__main__.py
dnadna/_version.py
dnadna/data_preprocessing.py
dnadna/datasets.py
dnadna/gradcam.py
dnadna/nets.py
dnadna/optim.py
dnadna/params.py
dnadna/prediction.py
dnadna/simulation.py
dnadna/simulator.py
dnadna/snp_sample.py
dnadna/summary_statistics.py
dnadna/training.py
dnadna/transforms.py
dnadna/version.py
dnadna/cli/__init__.py
dnadna/cli/init.py
dnadna/cli/predict.py
dnadna/cli/preprocess.py
dnadna/cli/simulation.py
dnadna/cli/sumstats.py
dnadna/cli/train.py
dnadna/defaults/__init__.py
dnadna/defaults/dataset.yml
dnadna/defaults/preprocessing.yml
dnadna/defaults/training.yml
dnadna/examples/__init__.py
dnadna/examples/one_event.py
dnadna/schemas/__init__.py
dnadna/schemas/dataset.yml
dnadna/schemas/definitions.yml
dnadna/schemas/param-set.yml
dnadna/schemas/plugins.yml
dnadna/schemas/preprocessing.yml
dnadna/schemas/simulation.yml
dnadna/schemas/summary-statistics.yml
dnadna/schemas/training-run.yml
dnadna/schemas/training.yml
dnadna/schemas/dataset_formats/dnadna.yml
dnadna/schemas/nets/base.yml
dnadna/schemas/nets/cnn.yml
dnadna/schemas/nets/custom_cnn.yml
dnadna/schemas/nets/mlp.yml
dnadna/schemas/nets/spidna.yml
dnadna/utils/__init__.py
dnadna/utils/cli.py
dnadna/utils/config.py
dnadna/utils/decorators.py
dnadna/utils/jsonschema.py
dnadna/utils/misc.py
dnadna/utils/plugins.py
dnadna/utils/serializers.py
dnadna/utils/tensor.py
dnadna/utils/testing.py
dnadna/utils/yaml.py
dnadna/utils/sphinx/__init__.py
dnadna-1.0.0rc1.dist-info/COPYING.LESSER
dnadna-1.0.0rc1.dist-info/LICENSE.md
dnadna-1.0.0rc1.dist-info/METADATA
dnadna-1.0.0rc1.dist-info/WHEEL
dnadna-1.0.0rc1.dist-info/entry_points.txt
dnadna-1.0.0rc1.dist-info/top_level.txt
dnadna-1.0.0rc1.dist-info/RECORD
