Metadata-Version: 2.1
Name: dnadna
Version: 1.0.0rc1
Summary: Deep Neural Architecture for DNA
Home-page: https://gitlab.com/mlgenetics/dnadna
Author: The DNADNA Developers
Maintainer-email: embray@lri.fr
Classifier: Development Status :: 5 - Production/Stable
Classifier: Environment :: Console
Classifier: Environment :: GPU :: NVIDIA CUDA
Classifier: Intended Audience :: Science/Research
Classifier: License :: CeCILL-C Free Software License Agreement (CECILL-C)
Classifier: License :: OSI Approved :: GNU Lesser General Public License v3 or later (LGPLv3+)
Classifier: Programming Language :: Python :: 3.7
Classifier: Topic :: Scientific/Engineering :: Bio-Informatics
Requires-Python: >=3.7
License-File: LICENSE.md
License-File: COPYING.LESSER
Requires-Dist: jsonschema (>=3.0.0)
Requires-Dist: jsonschema-pyref (>=0.1.0b1)
Requires-Dist: matplotlib (>=3.1.0)
Requires-Dist: msprime (>=0.7.0)
Requires-Dist: numpy (>=1.19.0)
Requires-Dist: pandas (>=0.25.0)
Requires-Dist: pyyaml (>=5.1.0)
Requires-Dist: scikit-allel (>=1.2.0)
Requires-Dist: torch (>=1.2.0)
Requires-Dist: tqdm (>=4.40.0)
Provides-Extra: docs
Requires-Dist: mistune (<2.0) ; extra == 'docs'
Requires-Dist: m2r ; extra == 'docs'
Requires-Dist: pygments-csv-lexer ; extra == 'docs'
Requires-Dist: sphinx (>=2.4.0) ; extra == 'docs'
Requires-Dist: sphinx-rtd-theme ; extra == 'docs'
Requires-Dist: sphinxcontrib-napoleon ; extra == 'docs'
Requires-Dist: sphinxcontrib-spelling ; extra == 'docs'
Provides-Extra: tests
Requires-Dist: filelock (>=3.0.12) ; extra == 'tests'
Requires-Dist: mistletoe ; extra == 'tests'
Requires-Dist: pytest (>=5.3.1) ; extra == 'tests'
Requires-Dist: pytest-cov (>=2.8.1) ; extra == 'tests'
Requires-Dist: pytest-doctestplus ; extra == 'tests'
Requires-Dist: pytest-xdist (>=1.31.0) ; extra == 'tests'
